LICENSE.txt
MANIFEST.in
README.rst
setup.py
docs/Makefile
docs/conf.py
docs/index.rst
docs/requirements.txt
docs/api/rbottle.rst
src/rbottle/__init__.py
src/rbottle/rbottle.py
src/rbottle.egg-info/PKG-INFO
src/rbottle.egg-info/SOURCES.txt
src/rbottle.egg-info/dependency_links.txt
src/rbottle.egg-info/requires.txt
src/rbottle.egg-info/top_level.txt
src/rbottle.egg-info/zip-safe
unittests/test_rbottle.py
unittests/test_rbottle.pyc
unittests/__pycache__/test_rbottle.cpython-27-PYTEST.pyc