Metadata-Version: 1.1
Name: rbottle
Version: 0.2.0
Summary: Decorators to make REST easier in Bottle.
Home-page: https://github.com/Bystroushaak/rbottle
Author: Bystroushaak
Author-email: bystrousak@kitakitsune.org
License: MIT
Platform: UNKNOWN
Classifier: Framework :: Bottle
Classifier: Topic :: Internet :: WWW/HTTP :: WSGI
Classifier: Topic :: Internet :: WWW/HTTP :: WSGI :: Application
Classifier: Topic :: Software Development :: Libraries
Classifier: Programming Language :: Python :: 2.7
Classifier: License :: OSI Approved :: MIT License
